{
    "city": {
        "grid_size": 30
    },
    "drones": {
        "fleet": [
            {
                "id": "D1",
                "max_payload": 15,
                "max_distance": 80,
                "speed": 3,
                "available": true
            },
            {
                "id": "D2",
                "max_payload": 10,
                "max_distance": 50,
                "speed": 2.5,
                "available": true
            },
            {
                "id": "D3",
                "max_payload": 7,
                "max_distance": 30,
                "speed": 2,
                "available": true
            }
        ]
    },
    "orders": [
        {
            "id": "O1",
            "delivery_x": 4,
            "delivery_y": 6,
            "deadline": 20,
            "package_weight": 5
        },
        {
            "id": "O2",
            "delivery_x": 7,
            "delivery_y": 3,
            "deadline": 25,
            "package_weight": 6
        },
        {
            "id": "O3",
            "delivery_x": 10,
            "delivery_y": 8,
            "deadline": 30,
            "package_weight": 4
        },
        {
            "id": "O4",
            "delivery_x": 15,
            "delivery_y": 10,
            "deadline": 35,
            "package_weight": 8
        }
    ]
}
